geode_mymodule/__init__.py
geode_mymodule/mylib.py
Geode_MyModule-2.0.0.dist-info/METADATA
Geode_MyModule-2.0.0.dist-info/WHEEL
Geode_MyModule-2.0.0.dist-info/top_level.txt
Geode_MyModule-2.0.0.dist-info/RECORD
