Metadata-Version: 2.1
Name: Geode-MyModule
Version: 2.0.0
Summary: Template for creating your own OpenGeode private module
Home-page: https://github.com/Geode-solutions/Geode-MyModule
Author: Geode-solutions
Author-email: contact@geode-solutions.com
License: Proprietary
Requires-Dist: geode-common (==25.*,>=25.0.0)
Requires-Dist: opengeode-core (==14.*,>=14.0.0)
